pylint_htmf/__init__.py
pylint_htmf/cli.py
pylint_htmf/plugin.py
pylint_htmf-0.1.1.dist-info/entry_points.txt
pylint_htmf-0.1.1.dist-info/LICENSE
pylint_htmf-0.1.1.dist-info/WHEEL
pylint_htmf-0.1.1.dist-info/METADATA
pylint_htmf-0.1.1.dist-info/RECORD
